{"trial_id": "9eb80bd587d777f12d59de8030900400", "hyperparameters": {"space": [{"class_name": "Choice", "config": {"name": "optimizer", "default": "sgd", "conditions": [], "values": ["sgd", "adam"], "ordered": false}}, {"class_name": "Float", "config": {"name": "learning_rate", "default": 0.001, "conditions": [], "min_value": 0.001, "max_value": 1.0, "step": null, "sampling": "log"}}], "values": {"optimizer": "sgd", "learning_rate": 0.010322328955049913, "tuner/epochs": 10, "tuner/initial_epoch": 0, "tuner/bracket": 0, "tuner/round": 0}}, "metrics": {"metrics": {"loss": {"direction": "min", "observations": [{"value": [0.6793342232704163], "step": 0}]}, "val_loss": {"direction": "min", "observations": [{"value": [0.6778731942176819], "step": 0}]}}}, "score": 0.6778731942176819, "best_step": 0, "status": "COMPLETED"}